setup.py
src/mailserver/__init__.py
src/mailserver/exceptions.py
src/mailserver/handlers.py
src/mailserver/mailbox.py
src/mailserver/mailers.py
src/mailserver/message.py
src/mailserver/models.py
src/mailserver/resolvers.py
src/mailserver.egg-info/PKG-INFO
src/mailserver.egg-info/SOURCES.txt
src/mailserver.egg-info/dependency_links.txt
src/mailserver.egg-info/requires.txt
src/mailserver.egg-info/top_level.txt
src/mailserver/management/__init__.py
src/mailserver/management/commands/__init__.py
src/mailserver/management/commands/readmail.py
src/mailserver/management/commands/startmailapp.py