Metadata-Version: 1.0
Name: mailserver
Version: 0.1alpha1
Summary: Create mail services in Django.
Home-page: http://github.com/telenieko/django-mailserver
Author: Marc Fargas
Author-email: telenieko@telenieko.com
License: BSD
Platform: UNKNOWN
Classifier: Development Status :: 2 - Pre-Alpha
Classifier: Framework :: Django
Classifier: Intended Audience :: Developers
Classifier: License :: OSI Approved :: BSD License
Classifier: Operating System :: OS Independent
Classifier: Programming Language :: Python
Classifier: Topic :: Internet :: WWW/HTTP
